halsim_ws/__init__.py
halsim_ws/py.typed
halsim_ws/version.py
halsim_ws/client/__init__.py
halsim_ws/client/main.py
halsim_ws/client/lib/libhalsim_ws_client.so
halsim_ws/server/__init__.py
halsim_ws/server/main.py
halsim_ws/server/lib/libhalsim_ws_server.so
robotpy_halsim_ws-2026.2.1.dist-info/METADATA
robotpy_halsim_ws-2026.2.1.dist-info/WHEEL
robotpy_halsim_ws-2026.2.1.dist-info/entry_points.txt
robotpy_halsim_ws-2026.2.1.dist-info/RECORD
