Metadata-Version: 2.4
Name: robotpy-halsim-ws
Version: 2026.2.1
Summary: WPILib simulator websim Extensions
Project-URL: Source code, https://github.com/robotpy/mostrobotpy
Author-email: RobotPy Development Team <robotpy@googlegroups.com>
License-Expression: BSD-3-Clause
Requires-Dist: robotpy-native-wpihal==2026.2.1
Requires-Dist: robotpy-native-wpinet==2026.2.1
